ic_slide/__init__.py
ic_slide/api_urls.py
ic_slide/auth.py
ic_slide/config.py
ic_slide/slide_index.py
ic_slide/slide_source.py
ic_slide/time_utils.py
ic_slide/try_pickle.py
omnipath_slide-1.0.0.dist-info/LICENSE
omnipath_slide-1.0.0.dist-info/METADATA
omnipath_slide-1.0.0.dist-info/WHEEL
omnipath_slide-1.0.0.dist-info/top_level.txt
omnipath_slide-1.0.0.dist-info/RECORD
