Metadata-Version: 2.1
Name: omnipath-slide
Version: 1.0.0
Summary: api of coriander slides, communicate with private cloud slides. 
Home-page: https://www.intemedic.com
Author: intemedic
Author-email: admin@intemedic.com
License: UNKNOWN
Platform: UNKNOWN
Classifier: Programming Language :: Python :: 3
Classifier: License :: OSI Approved :: MIT License
Classifier: Operating System :: OS Independent
Requires-Python: >=3.6
Requires-Dist: requests (>=2.22.0)
Requires-Dist: Pillow (>=6.2.0)
Requires-Dist: numpy (>=1.16.5)
